{
  "case": "Case4",
  "mode": "wl",
  "unit": "um",
  "interposer": {
    "width": 57000.0,
    "height": 59000.0,
    "fence": [
      0.0,
      57000.0,
      0.0,
      59000.0
    ]
  },
  "thermal": {
    "temp_aware_opt": false,
    "thermal_solver": "hotspot",
    "thermal_dir": "/data/xinli/ThermOpt/external/ATPlace_pub/thermal/",
    "num_grid_x": 64,
    "num_grid_y": 64
  },
  "chiplets": [
    {
      "name": "CPU1_0",
      "x": 24750.0,
      "y": 22750.0,
      "width": 12000.0,
      "height": 12000.0,
      "angle_rad": 4.71238899230957,
      "power_w": 105.0
    },
    {
      "name": "CPU1_1",
      "x": 24750.0,
      "y": 34850.0,
      "width": 12000.0,
      "height": 12000.0,
      "angle_rad": 0.0,
      "power_w": 105.0
    },
    {
      "name": "GPU_0",
      "x": 39850.0,
      "y": 12440.55078125,
      "width": 18000.0,
      "height": 18000.0,
      "angle_rad": 0.0,
      "power_w": 300.0
    },
    {
      "name": "GPU_1",
      "x": 39850.0,
      "y": 30540.55078125,
      "width": 18000.0,
      "height": 18000.0,
      "angle_rad": 1.5707963705062866,
      "power_w": 300.0
    },
    {
      "name": "GPU_2",
      "x": 25193.583984375,
      "y": 49950.0,
      "width": 18000.0,
      "height": 18000.0,
      "angle_rad": 3.1415927410125732,
      "power_w": 300.0
    },
    {
      "name": "GPU_3",
      "x": 9650.0,
      "y": 31850.0,
      "width": 18000.0,
      "height": 18000.0,
      "angle_rad": 4.71238899230957,
      "power_w": 300.0
    },
    {
      "name": "HBM_0",
      "x": 52950.0,
      "y": 14061.3798828125,
      "width": 8000.0,
      "height": 12000.0,
      "angle_rad": 3.1415927410125732,
      "power_w": 25.0
    },
    {
      "name": "HBM_1",
      "x": 40293.58203125,
      "y": 43640.55078125,
      "width": 8000.0,
      "height": 12000.0,
      "angle_rad": 4.71238899230957,
      "power_w": 25.0
    },
    {
      "name": "HBM_2",
      "x": 12093.5830078125,
      "y": 48651.2109375,
      "width": 8000.0,
      "height": 12000.0,
      "angle_rad": 0.0,
      "power_w": 25.0
    },
    {
      "name": "HBM_3",
      "x": 8377.7138671875,
      "y": 18750.0,
      "width": 8000.0,
      "height": 12000.0,
      "angle_rad": 1.5707963705062866,
      "power_w": 25.0
    },
    {
      "name": "HBM_4",
      "x": 22150.107421875,
      "y": 12650.0,
      "width": 8000.0,
      "height": 12000.0,
      "angle_rad": 1.5707963705062866,
      "power_w": 25.0
    }
  ],
  "raw_best_fp": [
    [
      24750.0,
      24750.0,
      39850.0,
      39850.0,
      25193.583984375,
      9650.0,
      52950.0,
      40293.58203125,
      12093.5830078125,
      8377.7138671875,
      22150.107421875,
      22750.0,
      34850.0,
      12440.55078125,
      30540.55078125,
      49950.0,
      31850.0,
      14061.3798828125,
      43640.55078125,
      48651.2109375,
      18750.0,
      12650.0
    ],
    [
      4.71238899230957,
      0.0,
      0.0,
      1.5707963705062866,
      3.1415927410125732,
      4.71238899230957,
      3.1415927410125732,
      4.71238899230957,
      0.0,
      1.5707963705062866,
      1.5707963705062866
    ]
  ]
}
